[
  {
    "date": "2026-01-13",
    "pps": 1.00059,
    "timestamp": 1768326584827
  },
  {
    "date": "2026-02-03",
    "pps": 1.005445,
    "timestamp": 1770095013542
  },
  {
    "date": "2026-02-06",
    "pps": 1.006244,
    "timestamp": 1770421002059
  },
  {
    "date": "2026-02-08",
    "pps": 1.006696,
    "timestamp": 1770586884684
  },
  {
    "date": "2026-04-08",
    "pps": 1.017799,
    "timestamp": 1775662986415
  },
  {
    "date": "2026-04-12",
    "pps": 1.018334,
    "timestamp": 1776030863570
  },
  {
    "date": "2026-04-17",
    "pps": 1.020623,
    "timestamp": 1776448941928
  },
  {
    "date": "2026-04-19",
    "pps": 1.020623,
    "timestamp": 1776632237614
  },
  {
    "date": "2026-04-20",
    "pps": 1.020623,
    "timestamp": 1776720997082
  },
  {
    "date": "2026-04-21",
    "pps": 1.020623,
    "timestamp": 1776811530862
  },
  {
    "date": "2026-04-22",
    "pps": 1.020849,
    "timestamp": 1776874237991
  },
  {
    "date": "2026-04-23",
    "pps": 1.020849,
    "timestamp": 1776975673894
  },
  {
    "date": "2026-04-24",
    "pps": 1.020849,
    "timestamp": 1777064173531
  },
  {
    "date": "2026-04-25",
    "pps": 1.020849,
    "timestamp": 1777126277480
  },
  {
    "date": "2026-04-26",
    "pps": 1.020849,
    "timestamp": 1777184542524
  },
  {
    "date": "2026-04-27",
    "pps": 1.020849,
    "timestamp": 1777255145979
  },
  {
    "date": "2026-04-28",
    "pps": 1.020849,
    "timestamp": 1777405368569
  },
  {
    "date": "2026-04-30",
    "pps": 1.021755,
    "timestamp": 1777565744852
  },
  {
    "date": "2026-05-01",
    "pps": 1.022662,
    "timestamp": 1777669286477
  },
  {
    "date": "2026-05-02",
    "pps": 1.022662,
    "timestamp": 1777745978572
  },
  {
    "date": "2026-05-03",
    "pps": 1.022662,
    "timestamp": 1777844098966
  },
  {
    "date": "2026-05-04",
    "pps": 1.022662,
    "timestamp": 1777924505285
  },
  {
    "date": "2026-05-05",
    "pps": 1.022662,
    "timestamp": 1777996949973
  },
  {
    "date": "2026-05-06",
    "pps": 1.022662,
    "timestamp": 1778089686800
  },
  {
    "date": "2026-05-07",
    "pps": 1.023568,
    "timestamp": 1778194971863
  },
  {
    "date": "2026-05-08",
    "pps": 1.024474,
    "timestamp": 1778284518052
  },
  {
    "date": "2026-05-09",
    "pps": 1.024474,
    "timestamp": 1778370541678
  },
  {
    "date": "2026-05-10",
    "pps": 1.024474,
    "timestamp": 1778457117595
  },
  {
    "date": "2026-05-11",
    "pps": 1.024474,
    "timestamp": 1778543835467
  },
  {
    "date": "2026-05-12",
    "pps": 1.024474,
    "timestamp": 1778626823420
  },
  {
    "date": "2026-05-13",
    "pps": 1.02538,
    "timestamp": 1778716672129
  },
  {
    "date": "2026-05-14",
    "pps": 1.02538,
    "timestamp": 1778803062934
  },
  {
    "date": "2026-05-15",
    "pps": 1.02538,
    "timestamp": 1778889245360
  },
  {
    "date": "2026-05-16",
    "pps": 1.026286,
    "timestamp": 1778975528588
  },
  {
    "date": "2026-05-17",
    "pps": 1.026286,
    "timestamp": 1779062190320
  },
  {
    "date": "2026-05-18",
    "pps": 1.026286,
    "timestamp": 1779141712634
  },
  {
    "date": "2026-05-19",
    "pps": 1.026286,
    "timestamp": 1779228935873
  },
  {
    "date": "2026-05-20",
    "pps": 1.026286,
    "timestamp": 1779318736369
  },
  {
    "date": "2026-05-21",
    "pps": 1.026286,
    "timestamp": 1779404574875
  },
  {
    "date": "2026-05-22",
    "pps": 1.026707,
    "timestamp": 1779487658451
  },
  {
    "date": "2026-05-23",
    "pps": 1.026707,
    "timestamp": 1779580584712
  },
  {
    "date": "2026-05-24",
    "pps": 1.026707,
    "timestamp": 1779663506938
  },
  {
    "date": "2026-05-25",
    "pps": 1.026707,
    "timestamp": 1779750047124
  },
  {
    "date": "2026-05-26",
    "pps": 1.026707,
    "timestamp": 1779833919645
  },
  {
    "date": "2026-05-27",
    "pps": 1.026707,
    "timestamp": 1779923760763
  },
  {
    "date": "2026-05-28",
    "pps": 1.028392,
    "timestamp": 1780010150696
  },
  {
    "date": "2026-05-29",
    "pps": 1.029217,
    "timestamp": 1780096273361
  },
  {
    "date": "2026-05-30",
    "pps": 1.029217,
    "timestamp": 1780185588749
  },
  {
    "date": "2026-05-31",
    "pps": 1.029217,
    "timestamp": 1780269040840
  },
  {
    "date": "2026-06-01",
    "pps": 1.029217,
    "timestamp": 1780354843945
  },
  {
    "date": "2026-06-02",
    "pps": 1.029217,
    "timestamp": 1780441293364
  },
  {
    "date": "2026-06-03",
    "pps": 1.029217,
    "timestamp": 1780530151462
  },
  {
    "date": "2026-06-04",
    "pps": 1.029217,
    "timestamp": 1780611623192
  },
  {
    "date": "2026-06-05",
    "pps": 1.03044,
    "timestamp": 1780700886397
  },
  {
    "date": "2026-06-06",
    "pps": 1.03044,
    "timestamp": 1780786968061
  },
  {
    "date": "2026-06-07",
    "pps": 1.03044,
    "timestamp": 1780869798145
  },
  {
    "date": "2026-06-08",
    "pps": 1.03044,
    "timestamp": 1780957555861
  },
  {
    "date": "2026-06-09",
    "pps": 1.03044,
    "timestamp": 1781043874522
  },
  {
    "date": "2026-06-10",
    "pps": 1.03044,
    "timestamp": 1781128892874
  },
  {
    "date": "2026-06-11",
    "pps": 1.03044,
    "timestamp": 1781220022981
  },
  {
    "date": "2026-06-12",
    "pps": 1.03206,
    "timestamp": 1781306163876
  },
  {
    "date": "2026-06-13",
    "pps": 1.03206,
    "timestamp": 1781388187515
  },
  {
    "date": "2026-06-14",
    "pps": 1.03206,
    "timestamp": 1781474910625
  },
  {
    "date": "2026-06-15",
    "pps": 1.03206,
    "timestamp": 1781567072438
  },
  {
    "date": "2026-06-16",
    "pps": 1.03206,
    "timestamp": 1781647856464
  },
  {
    "date": "2026-06-17",
    "pps": 1.03206,
    "timestamp": 1781738602134
  },
  {
    "date": "2026-06-18",
    "pps": 1.03206,
    "timestamp": 1781820417840
  },
  {
    "date": "2026-06-19",
    "pps": 1.033518,
    "timestamp": 1781909792215
  },
  {
    "date": "2026-06-20",
    "pps": 1.033518,
    "timestamp": 1781993136277
  },
  {
    "date": "2026-06-21",
    "pps": 1.033518,
    "timestamp": 1782083498243
  },
  {
    "date": "2026-06-22",
    "pps": 1.033518,
    "timestamp": 1782165682965
  },
  {
    "date": "2026-06-23",
    "pps": 1.033518,
    "timestamp": 1782258970176
  },
  {
    "date": "2026-06-24",
    "pps": 1.033518,
    "timestamp": 1782339398041
  },
  {
    "date": "2026-06-25",
    "pps": 1.033518,
    "timestamp": 1782426017973
  },
  {
    "date": "2026-06-26",
    "pps": 1.034978,
    "timestamp": 1782515081135
  },
  {
    "date": "2026-06-27",
    "pps": 1.034978,
    "timestamp": 1782601283651
  },
  {
    "date": "2026-06-28",
    "pps": 1.034978,
    "timestamp": 1782684073270
  },
  {
    "date": "2026-06-29",
    "pps": 1.034978,
    "timestamp": 1782773812033
  },
  {
    "date": "2026-06-30",
    "pps": 1.034978,
    "timestamp": 1782861093771
  },
  {
    "date": "2026-07-01",
    "pps": 1.034978,
    "timestamp": 1782941234745
  },
  {
    "date": "2026-07-02",
    "pps": 1.034978,
    "timestamp": 1783033520379
  },
  {
    "date": "2026-07-03",
    "pps": 1.037411,
    "timestamp": 1783119739567
  },
  {
    "date": "2026-07-04",
    "pps": 1.037411,
    "timestamp": 1783206389180
  },
  {
    "date": "2026-07-05",
    "pps": 1.037411,
    "timestamp": 1783288836927
  },
  {
    "date": "2026-07-06",
    "pps": 1.037411,
    "timestamp": 1783379177110
  },
  {
    "date": "2026-07-07",
    "pps": 1.037411,
    "timestamp": 1783465210140
  },
  {
    "date": "2026-07-08",
    "pps": 1.037411,
    "timestamp": 1783551992062
  },
  {
    "date": "2026-07-09",
    "pps": 1.037411,
    "timestamp": 1783636007673
  },
  {
    "date": "2026-07-10",
    "pps": 1.037411,
    "timestamp": 1783671715296
  }
]